frida_dexdump/__init__.py
frida_dexdump/__main__.py
frida_dexdump/banner.py
frida_dexdump/agent/__init__.py
frida_dexdump/agent/agent.js
frida_dexdump-2.0.1.dist-info/LICENSE
frida_dexdump-2.0.1.dist-info/METADATA
frida_dexdump-2.0.1.dist-info/WHEEL
frida_dexdump-2.0.1.dist-info/entry_points.txt
frida_dexdump-2.0.1.dist-info/top_level.txt
frida_dexdump-2.0.1.dist-info/RECORD
